spriteutils/__init__.py
spriteutils/spriteutil.py
spriteutils_pkg-2.0.1.dist-info/LICENSE
spriteutils_pkg-2.0.1.dist-info/METADATA
spriteutils_pkg-2.0.1.dist-info/WHEEL
spriteutils_pkg-2.0.1.dist-info/top_level.txt
spriteutils_pkg-2.0.1.dist-info/RECORD
