Metadata-Version: 2.1
Name: spriteutils-pkg
Version: 2.0.1
Summary: Utilities for finding sprites in a sprite sheet
Home-page: https://github.com/intek-training-jsc/sprite-sheet-Long-Nguyen-96
Author: Long Nguyen
Author-email: long.nguyen@f4.intek.edu.com
License: UNKNOWN
Platform: UNKNOWN
Classifier: Programming Language :: Python :: 3
Classifier: License :: OSI Approved :: MIT License
Classifier: Operating System :: OS Independent
Requires-Python: >=3.7
Requires-Dist: numpy (==1.18.1)
Requires-Dist: pillow (==7.0.0)
